{
  "comments": [
    {
      "id": "3edbd0de-df39-f586-5deb-8b5ca4c2c356",
      "shopId": "27091506",
      "nickName": "",
      "comment": "에이블헬스장",
      "userId": "qsn5T77abRgBEYiDHYCClt2EB252"
    },
    {
      "shopId": "27091506",
      "nickName": "",
      "comment": "코멘트아이디 실험용",
      "userId": "qsn5T77abRgBEYiDHYCClt2EB252",
      "id": "N14XCGz"
    },
    {
      "shopId": "25887294",
      "nickName": "",
      "comment": "1",
      "rating": 3,
      "userId": "knVhnnVoarOno208AlpcB8NesDN2",
      "id": "5MnwGNA"
    },
    {
      "shopId": "25887294",
      "nickName": "",
      "comment": "2",
      "rating": 4,
      "userId": "knVhnnVoarOno208AlpcB8NesDN2",
      "id": "zHXZZdS"
    }
  ],
  "users": [
    {
      "id": "qsn5T77abRgBEYiDHYCClt2EB252",
      "name": "이동준",
      "email": "leedj1345@naver.com",
      "pw": "password1!"
    },
    {
      "id": "ODmzCjWvAQeiw4aMruw5lBvxrM12",
      "name": "이동준2",
      "email": "ourstar1345@gmail.com",
      "pw": "password1!"
    },
    {
      "id": "QOBAJA75L7a2KOCFXNZjtIksvbu1",
      "name": "이동준3",
      "email": "operational4@naver.com",
      "pw": "password1!"
    },
    {
      "id": "knVhnnVoarOno208AlpcB8NesDN2",
      "name": "이은한",
      "email": "reactprotein@gmail.com",
      "pw": "as12df78**"
    }
  ]
}